spacemenu/__init__.py
spacemenu/branch.py
spacemenu/leaf.py
spacemenu/node.py
spacemenu/options.py
spacemenu/window.py
test/__init__.py
test/test_branch.py
test/test_window.py
spacemenu-0.4.dist-info/LICENSE
spacemenu-0.4.dist-info/METADATA
spacemenu-0.4.dist-info/WHEEL
spacemenu-0.4.dist-info/top_level.txt
spacemenu-0.4.dist-info/RECORD
