Metadata-Version: 2.1
Name: spacemenu
Version: 0.4
Summary: A spacemacs menu inspired gtk module
Home-page: https://github.com/pm-coelho/spacemenu
Author: pmcoelho
Author-email: pmcoelho@protonmail.com
License: GPLv3+
Platform: UNKNOWN
Classifier: Development Status :: 3 - Alpha
Classifier: Environment :: X11 Applications
Classifier: Environment :: X11 Applications :: GTK
Classifier: Intended Audience :: Developers
Classifier: License :: OSI Approved :: GNU General Public License v3 or later (GPLv3+)
Classifier: Operating System :: POSIX :: Linux
Classifier: Topic :: Software Development :: Libraries :: Python Modules
Requires-Dist: pycairo
Requires-Dist: PyGObject
